Metadata-Version: 2.1
Name: cloudprogress
Version: 0.0.1
Summary: Python rest client for Cloud Progress https://cloudprogress.io, 
Home-page: https://github.com/cloudprogress/cpr-py
Author: Abe Winter
Author-email: awinter.public+cprpy@gmail.com
License: UNKNOWN
Keywords: cloudprogress,progress bar,progress,loading bar,eta
Platform: UNKNOWN
Requires-Python: >=3.7
